entity_query_language/__init__.py
entity_query_language/cache_data.py
entity_query_language/conclusion.py
entity_query_language/conclusion_selector.py
entity_query_language/entity.py
entity_query_language/enums.py
entity_query_language/failures.py
entity_query_language/hashed_data.py
entity_query_language/predicate.py
entity_query_language/rule.py
entity_query_language/rxnode.py
entity_query_language/symbolic.py
entity_query_language/utils.py
entity_query_language-3.0.1.dist-info/licenses/LICENSE
entity_query_language-3.0.1.dist-info/METADATA
entity_query_language-3.0.1.dist-info/WHEEL
entity_query_language-3.0.1.dist-info/top_level.txt
entity_query_language-3.0.1.dist-info/RECORD
