Metadata-Version: 2.4
Name: entity_query_language
Version: 3.0.1
Summary: Provides a relational query language that is pythonic and intuitive. Entity Query Language serves as a front end to other query languages like sql or prolog
Author-email: Abdelrhman Bassiouny <abassiou@uni-bremen.de>
License:                     GNU GENERAL PUBLIC LICENSE
Project-URL: Homepage, https://github.com/AbdelrhmanBassiouny/entity_query_language
Keywords: robotics,knowledge,reasoning,representation,query language,relational database
Classifier: Programming Language :: Python :: 3
License-File: LICENSE
Requires-Dist: anytree>=2.8.0
Requires-Dist: typing-extensions>=4.12.2
Requires-Dist: rustworkx>=0.14.0
Dynamic: license-file
